PyFunnels/PyF_nmap.py
PyFunnels/PyF_photon.py
PyFunnels/PyF_recon_ng.py
PyFunnels/PyF_spiderfoot.py
PyFunnels/PyF_theharvester.py
PyFunnels/PyFunnels.py
PyFunnels/__init__.py
PyFunnels-0.0.2.dist-info/LICENSE
PyFunnels-0.0.2.dist-info/METADATA
PyFunnels-0.0.2.dist-info/WHEEL
PyFunnels-0.0.2.dist-info/top_level.txt
PyFunnels-0.0.2.dist-info/RECORD
