Metadata-Version: 2.1
Name: PyFunnels
Version: 0.0.2
Summary: Aggregates the output of one or more tools.
Home-page: https://github.com/packetvitality/PyFunnels
Author: TJ Nicholls
License: UNKNOWN
Download-URL: https://github.com/packetvitality/PyFunnels/archive/0.0.2.tar.gz
Platform: UNKNOWN
Classifier: Programming Language :: Python :: 3
Classifier: License :: OSI Approved :: MIT License
Classifier: Operating System :: OS Independent
